conv_stft/__init__.py
conv_stft/conv_stft.py
conv_stft-0.1.2.dist-info/LICENSE
conv_stft-0.1.2.dist-info/METADATA
conv_stft-0.1.2.dist-info/WHEEL
conv_stft-0.1.2.dist-info/top_level.txt
conv_stft-0.1.2.dist-info/RECORD
