Metadata-Version: 2.1
Name: conv-stft
Version: 0.1.2
Summary: A Conv-STFT/iSTFT implement based on Torch
Home-page: https://github.com/echocatzh/conv-stft
Author: Shimin Zhang
Author-email: shmzhang@npu-aslp.org
License: MIT
Platform: UNKNOWN
Requires-Python: >=3.5
Requires-Dist: numpy
Requires-Dist: scipy
